auditlog/__init__.py
auditlog/decorators.py
auditlog/models.py
migrations/__init__.py
audit_trail_logger-0.1.3.dist-info/LICENSE
audit_trail_logger-0.1.3.dist-info/METADATA
audit_trail_logger-0.1.3.dist-info/WHEEL
audit_trail_logger-0.1.3.dist-info/top_level.txt
audit_trail_logger-0.1.3.dist-info/RECORD
