Metadata-Version: 2.1
Name: audit-trail-logger
Version: 0.1.3
Summary: A Django package for logging actions with user and object details
Home-page: https://github.com/sardareurvashi05/audit-trail-logger
Author: Urvashi Sardare
Author-email: urvashisardare@gmail.com
License: UNKNOWN
Platform: UNKNOWN
Classifier: Programming Language :: Python :: 3
Classifier: License :: OSI Approved :: MIT License
Classifier: Operating System :: OS Independent
Requires-Python: >=3.6
License-File: LICENSE
Requires-Dist: Django>=3.0
